common/__init__.py
common/config/__init__.py
common/config/model_loader.py
common/engine/__init__.py
common/engine/config_executor.py
common/engine/operation_registry.py
common/init.py
common/models/__init__.py
common/models/base.py
common/models/configs/__init__.py
common/models/core/__init.__.py
common/models/core/tag.py
common/models/core/user.py
common/models/factory.py
common/models/mixins.py
common/models/registry.py
common/services/__init__.py
common/services/analytics/__init__.py
common/services/analytics/fundamental.py
common/services/analytics/growth.py
common/services/analytics/valuation.py
common/services/communication/__init__.py
common/services/communication/email_service.py
common/services/communication/messaging_service.py
common/services/communication/sms_service.py
common/services/data_fetcher/__init__.py
common/services/data_fetcher/alphavantage.py
common/services/data_fetcher/base.py
common/services/data_fetcher/curated_data.py
common/services/data_fetcher/polygon.py
common/services/data_fetcher/stock.py
common/services/data_fetcher/yfinance.py
common/services/data_processor/__init__.py
common/services/data_processor/portfolio_metrics.py
common/services/data_processor/returns.py
common/services/data_processor/risk_metrics.py
common/services/data_processor/standardization.py
common/services/data_processor/technical_indicators.py
common/services/db_service.py
common/services/decisioning/__init__.py
common/services/decisioning/decision_engine.py
common/services/decisioning/expression_engine.py
common/services/decisioning/graph_evaluator.py
common/services/decisioning/models.py
common/services/decisioning/table_evaluator.py
common/services/encryption/__init__.py
common/services/encryption/field_encryption.py
common/services/forecasting/__init__.py
common/services/forecasting/context.py
common/services/forecasting/core.py
common/services/forecasting/ensemble.py
common/services/forecasting/models.py
common/services/forecasting/service.py
timber_common-0.3.8.dist-info/METADATA
timber_common-0.3.8.dist-info/WHEEL
timber_common-0.3.8.dist-info/licenses/LICENSE
timber_common-0.3.8.dist-info/RECORD
