Metadata-Version: 2.4
Name: timber-common
Version: 0.3.8
Summary: Configuration-driven persistence library with ml tools (finance related) config driven db model registration, llm model choice, automatic encryption, caching, vector search, and GDPR compliance for Python applications
License: MIT
License-File: LICENSE
Keywords: orm,sqlalchemy,persistence,vector-search,semantic-search,encryption,gdpr,yaml-config,postgres,redis,configuration-driven,data-modeling,machine-learning,embeddings
Author: Pumulo Sikaneta
Author-email: pumulo@gmail.com
Maintainer: Pumulo Sikaneta
Maintainer-email: pumulo@gmail.com
Requires-Python: >=3.13,<4.0
Classifier: Development Status :: 4 - Beta
Classifier: Intended Audience :: Developers
Classifier: Intended Audience :: Financial and Insurance Industry
Classifier: License :: OSI Approved :: MIT License
Classifier: Operating System :: OS Independent
Classifier: Programming Language :: Python :: 3
Classifier: Programming Language :: Python :: 3.13
Classifier: Programming Language :: Python :: 3.14
Classifier: Programming Language :: Python :: 3 :: Only
Classifier: Topic :: Database
Classifier: Topic :: Database :: Front-Ends
Classifier: Topic :: Office/Business :: Financial
Classifier: Topic :: Scientific/Engineering :: Artificial Intelligence
Classifier: Topic :: Software Development :: Libraries :: Python Modules
Classifier: Typing :: Typed
Provides-Extra: all
Provides-Extra: pinecone
Provides-Extra: qdrant
Provides-Extra: weaviate
Requires-Dist: Authlib (>=1.6.5,<2.0.0)
Requires-Dist: Jinja2 (>=3.1.6,<4.0.0)
Requires-Dist: PyYAML (>=6.0.3,<7.0.0)
Requires-Dist: Werkzeug (>=3.1.3,<4.0.0)
Requires-Dist: boto3 (>=1.41.2,<2.0.0)
Requires-Dist: cryptography (>=46.0.2,<47.0.0)
Requires-Dist: fastembed (>=0.7.3,<0.8.0)
Requires-Dist: google-genai[grpc] (>=1.52.0,<2.0.0)
Requires-Dist: langchain (>=1.0.8,<2.0.0)
Requires-Dist: langchain-core (>=1.1.0,<2.0.0)
Requires-Dist: langchain-google-genai (>=3.1.0,<4.0.0)
Requires-Dist: langgraph (>=1.0.3,<2.0.0)
Requires-Dist: pandas (>=2.3.3,<3.0.0)
Requires-Dist: pgvector[sqlalchemy] (>=0.4.1,<0.5.0)
Requires-Dist: plaid-python (>=37.1.0,<38.0.0)
Requires-Dist: psycopg2-binary (>=2.9.11,<3.0.0)
Requires-Dist: pydantic (>=2.11.9,<3.0.0)
Requires-Dist: python-dotenv (>=1.1.1,<2.0.0)
Requires-Dist: redis (>=6.4.0,<7.0.0)
Requires-Dist: requests (>=2.32.5,<3.0.0)
Requires-Dist: scipy (>=1.16.3,<2.0.0)
Requires-Dist: sendgrid (>=6.12.5,<7.0.0)
Requires-Dist: setuptools (>=80.9.0,<81.0.0)
Requires-Dist: sqlalchemy (>=2.0.36,<3.0.0)
Requires-Dist: stripe (>=14.0.1,<15.0.0)
Requires-Dist: tiktoken (==0.12.0)
Requires-Dist: twilio (>=9.9.0,<10.0.0)
Requires-Dist: vonage (>=4.7.2,<5.0.0)
Requires-Dist: yfinance (>=0.2.66,<0.3.0)
Project-URL: Bug Tracker, https://github.com/pumulo/timber-common/issues
Project-URL: Changelog, https://github.com/pumulo/timber-common/blob/main/CHANGELOG.md
Project-URL: Documentation, https://github.com/pumulo/timber-common/tree/main/documentation
Project-URL: Discussions, https://github.com/pumulo/timber-common/discussions
Project-URL: Homepage, https://github.com/pumulo/timber-common
Project-URL: Repository, https://github.com/pumulo/timber-common
